klamath/LICENSE.md
klamath/README.md
klamath/__init__.py
klamath/basic.py
klamath/elements.py
klamath/library.py
klamath/py.typed
klamath/record.py
klamath/records.py
klamath/test_basic.py
klamath-1.5.dist-info/METADATA
klamath-1.5.dist-info/WHEEL
klamath-1.5.dist-info/licenses/LICENSE.md
klamath-1.5.dist-info/RECORD
