Metadata-Version: 2.4
Name: klamath
Version: 1.5
Summary: GDSII format reader/writer
Author-email: Jan Petykiewicz <jan@mpxd.net>
License: GNU General Public License
License-File: LICENSE.md
Keywords: CAD,Calma,EDA,IC,design,drawing,electronics,gds,gds2,gdsii,geometric,geometry,layout,litho,lithography,mask,pattern,photonics,polygon,stream,vector
Classifier: Development Status :: 5 - Production/Stable
Classifier: Intended Audience :: Developers
Classifier: Intended Audience :: Information Technology
Classifier: Intended Audience :: Manufacturing
Classifier: Intended Audience :: Science/Research
Classifier: License :: OSI Approved :: GNU General Public License v3 (GPLv3)
Classifier: Programming Language :: Python :: 3
Classifier: Topic :: Scientific/Engineering :: Electronic Design Automation (EDA)
Requires-Python: >=3.11
Requires-Dist: numpy>=1.26
